quickdiscord/__init__.py
quickdiscord/client.py
quickdiscord/lib/__init__.py
quickdiscord/lib/util/__init__.py
quickdiscord/lib/util/exceptions.py
quickdiscord/lib/util/objects.py
QuickDiscord.py-0.0.4.dist-info/LICENSE
QuickDiscord.py-0.0.4.dist-info/METADATA
QuickDiscord.py-0.0.4.dist-info/WHEEL
QuickDiscord.py-0.0.4.dist-info/top_level.txt
QuickDiscord.py-0.0.4.dist-info/RECORD
