Metadata-Version: 2.1
Name: QuickDiscord.py
Version: 0.0.4
Summary: The package that makes coding discord bots quicker!
Home-page: UNKNOWN
Author: Team Wezacon
Author-email: wezacon.com@gmail.com
License: MIT
Keywords: bots,discord-py,wezacon
Platform: UNKNOWN
Requires-Dist: discord.py
Requires-Dist: ujson
Requires-Dist: requests
